pylfsr/__init__.py
pylfsr/primitive_polynomials_GF2_dict.txt
pylfsr/pylfsr.py
pylfsr/seq_generators.py
pylfsr/utils.py
pylfsr-1.0.7.dist-info/LICENSE
pylfsr-1.0.7.dist-info/METADATA
pylfsr-1.0.7.dist-info/WHEEL
pylfsr-1.0.7.dist-info/top_level.txt
pylfsr-1.0.7.dist-info/RECORD
