Metadata-Version: 2.1
Name: pylfsr
Version: 1.0.7
Summary: Linear Feedback Shift Register
Home-page: https://github.com/Nikeshbajaj/Linear_Feedback_Shift_Register
Download-URL: https://github.com/Nikeshbajaj/Linear_Feedback_Shift_Register/tarball/1.0.7
Author: Nikesh Bajaj
Author-email: nikkeshbajaj@gmail.com
License: MIT
Project-URL: Documentation, https://lfsr.readthedocs.io
Project-URL: Say Thanks!, https://github.com/Nikeshbajaj
Project-URL: Source, https://github.com/Nikeshbajaj/Linear_Feedback_Shift_Register
Project-URL: Tracker, https://github.com/Nikeshbajaj/Linear_Feedback_Shift_Register/issues
Keywords: lfsr linear-feedback-shift-register random generator gf(2)
Classifier: Programming Language :: Python :: 3
Classifier: Programming Language :: Python :: 3.5
Classifier: Programming Language :: Python :: 3.6
Classifier: Programming Language :: Python :: 3.7
Classifier: Natural Language :: English
Classifier: License :: OSI Approved :: MIT License
Classifier: Operating System :: OS Independent
Classifier: Development Status :: 5 - Production/Stable
Classifier: Intended Audience :: Developers
Classifier: Intended Audience :: Science/Research
Classifier: Intended Audience :: Information Technology
Classifier: Intended Audience :: Education
Classifier: Intended Audience :: Telecommunications Industry
Classifier: Topic :: Security :: Cryptography
Classifier: Topic :: Software Development :: Libraries :: Python Modules
Classifier: Topic :: Games/Entertainment :: Puzzle Games
Classifier: Topic :: Communications
Classifier: Development Status :: 5 - Production/Stable
License-File: LICENSE
Requires-Dist: numpy
Requires-Dist: matplotlib
